tikkie/__init__.py
tikkie/_session.py
tikkie/_util.py
tikkie/_version.py
tikkie/errors.py
tikkie/v2/__init__.py
tikkie/v2/ideal_qr.py
tikkie/v2/ideal_qr_notification.py
tikkie/v2/models.py
tikkie/v2/payment.py
tikkie/v2/payment_request.py
tikkie/v2/payment_request_notification.py
tikkie/v2/refund.py
tikkie/v2/sandbox_app.py
tikkie/v2/transaction_bundle.py
tikkie/v2/transactions_notifications.py
tikkie-1.0.2.dist-info/LICENSE
tikkie-1.0.2.dist-info/METADATA
tikkie-1.0.2.dist-info/WHEEL
tikkie-1.0.2.dist-info/top_level.txt
tikkie-1.0.2.dist-info/RECORD
