Metadata-Version: 2.1
Name: tikkie
Version: 1.0.2
Summary: Tikkie API client
Home-page: https://github.com/new10com/python-tikkie-api
Author: New10
Author-email: pypi-admin@new10.com
License: UNKNOWN
Platform: UNKNOWN
Classifier: Development Status :: 5 - Production/Stable
Classifier: Programming Language :: Python :: 3
Classifier: Programming Language :: Python :: 3.8
Classifier: Programming Language :: Python :: 3.9
Classifier: License :: OSI Approved :: MIT License
Requires-Python: >=3.8.0
Requires-Dist: requests (>=2)
Requires-Dist: pydantic (>=1.0)
Requires-Dist: typing-extensions
Provides-Extra: tests
Requires-Dist: black (==20.8b1) ; extra == 'tests'
Requires-Dist: bump2version (==1.0.1) ; extra == 'tests'
Requires-Dist: flake8 (==3.9.2) ; extra == 'tests'
Requires-Dist: isort (==5.8.0) ; extra == 'tests'
Requires-Dist: mypy (==0.812) ; extra == 'tests'
Requires-Dist: pre-commit (==2.10.1) ; extra == 'tests'
Requires-Dist: pytest-cov (==2.11.1) ; extra == 'tests'
Requires-Dist: pytest-dotenv (==0.5.2) ; extra == 'tests'
Requires-Dist: pytest-pythonpath (==0.7.3) ; extra == 'tests'
Requires-Dist: pytest (==6.2.2) ; extra == 'tests'
